vl53_400_lib/__init__.py
vl53_400_lib/device_access.py
vl53_400_lib/main.py
vl53_400_lib-0.1.2.dist-info/LICENSE
vl53_400_lib-0.1.2.dist-info/METADATA
vl53_400_lib-0.1.2.dist-info/WHEEL
vl53_400_lib-0.1.2.dist-info/entry_points.txt
vl53_400_lib-0.1.2.dist-info/RECORD
