Metadata-Version: 2.1
Name: vl53_400_lib
Version: 0.1.2
Summary: Python library for using the VL53-400 laser rangerfinder via serial port
Author: Robert J. Berger
Author-email: rberger@ibd.com
Requires-Python: >=3.11,<4.0
Classifier: Programming Language :: Python :: 3
Classifier: Programming Language :: Python :: 3.11
Requires-Dist: loguru (>=0.7.0,<0.8.0)
Requires-Dist: modbus-crc (>=1.3,<2.0)
Requires-Dist: mypy (>=1.5.1,<2.0.0)
Requires-Dist: poetry (>=1.6.1,<2.0.0)
Requires-Dist: pyserial (>=3.5,<4.0)
